LICENSE
MANIFEST.in
README
setup.py
mdown/__init__.py
mdown/filters.py
mdown/forms.py
mdown/models.py
mdown/management/__init__.py
mdown/management/commands/__init__.py
mdown/management/commands/pygments_styles.py
mdown/static/mdown/jquery-1.4.4.min.js
mdown/static/mdown/wmd/License.txt
mdown/static/mdown/wmd/jquery.wmd.min.js
mdown/static/mdown/wmd/wmd.css
mdown/static/mdown/wmd/images/stripe.gif
mdown/static/mdown/wmd/images/wmd-buttons.png
mezzanine_mdown.egg-info/PKG-INFO
mezzanine_mdown.egg-info/SOURCES.txt
mezzanine_mdown.egg-info/dependency_links.txt
mezzanine_mdown.egg-info/not-zip-safe
mezzanine_mdown.egg-info/requires.txt
mezzanine_mdown.egg-info/top_level.txt