Metadata-Version: 1.0
Name: mezzanine-mdown
Version: 0.1a
Summary: Markdown for RichText content in Mezzanine.
Home-page: https://bitbucket.org/onelson/mezzanine-mdown/
Author: Owen Nelson
Author-email: onelson@gmail.com
License: MIT
Keywords: django,mezzanine,markdown,wmd
Platform: UNKNOWN
Classifier: Development Status :: 2 - Pre-Alpha
Classifier: Environment :: Web Environment
Classifier: Framework :: Django
Classifier: Intended Audience :: Developers
Classifier: License :: OSI Approved :: MIT License
Classifier: Operating System :: OS Independent
Classifier: Programming Language :: Python
Classifier: Topic :: Internet :: WWW/HTTP
Classifier: Topic :: Internet :: WWW/HTTP :: Dynamic Content
Classifier: Topic :: Internet :: WWW/HTTP :: WSGI
Classifier: Topic :: Software Development :: Libraries :: Application Frameworks
Classifier: Topic :: Software Development :: Libraries :: Python Modules
